tap_powerbi_metadata/__init__.py
tap_powerbi_metadata/streams.py
tap_powerbi_metadata/tap.py
tap_powerbi_metadata/tests/test_standard_tests.py
tap_powerbi_metadata-0.0.4.dist-info/LICENSE
tap_powerbi_metadata-0.0.4.dist-info/METADATA
tap_powerbi_metadata-0.0.4.dist-info/WHEEL
tap_powerbi_metadata-0.0.4.dist-info/entry_points.txt
tap_powerbi_metadata-0.0.4.dist-info/RECORD
