Metadata-Version: 2.1
Name: tap-powerbi-metadata
Version: 0.0.4
Summary: `tap-powerbi-metadata` is Singer-compliant PowerBIMetadata tap built with Singer SDK.
License: Apache v2
Author: AJ Steers
Author-email: aaaronsteers@gmail.com
Requires-Python: >=3.6,<3.9
Classifier: License :: Other/Proprietary License
Classifier: Programming Language :: Python :: 3
Classifier: Programming Language :: Python :: 3.6
Classifier: Programming Language :: Python :: 3.7
Classifier: Programming Language :: Python :: 3.8
Requires-Dist: singer-sdk (>=0.1.0,<0.2.0)
